LICENSE
MANIFEST.in
README.md
setup.cfg
setup.py
nqgym/__init__.py
nqgym/cli.py
nqgym/config.py
nqgym.egg-info/PKG-INFO
nqgym.egg-info/SOURCES.txt
nqgym.egg-info/dependency_links.txt
nqgym.egg-info/entry_points.txt
nqgym.egg-info/not-zip-safe
nqgym.egg-info/requires.txt
nqgym.egg-info/top_level.txt
nqgym/templates/nqproject/README.md
nqgym/templates/nqproject/cookiecutter.json
nqgym/templates/nqproject/hooks/pre_gen_project__.py
nqgym/templates/nqproject/{{cookiecutter.package_name}}/.gitignore
nqgym/templates/nqproject/{{cookiecutter.package_name}}/MANIFEST.in
nqgym/templates/nqproject/{{cookiecutter.package_name}}/Makefile
nqgym/templates/nqproject/{{cookiecutter.package_name}}/README.md
nqgym/templates/nqproject/{{cookiecutter.package_name}}/setup.cfg
nqgym/templates/nqproject/{{cookiecutter.package_name}}/setup.py
nqgym/templates/nqproject/{{cookiecutter.package_name}}/logs/.gitignore
nqgym/templates/nqproject/{{cookiecutter.package_name}}/resources/data/.gitignore
nqgym/templates/nqproject/{{cookiecutter.package_name}}/resources/generated/.gitignore
nqgym/templates/nqproject/{{cookiecutter.package_name}}/tests/conftest.py
nqgym/templates/nqproject/{{cookiecutter.package_name}}/tests/test_cli.py
nqgym/templates/nqproject/{{cookiecutter.package_name}}/{{cookiecutter.package_name}}/__init__.py
nqgym/templates/nqproject/{{cookiecutter.package_name}}/{{cookiecutter.package_name}}/cli.py
nqgym/templates/nqproject/{{cookiecutter.package_name}}/{{cookiecutter.package_name}}/hello.py
nqgym/templates/nqservice/README.md