Metadata-Version: 2.1
Name: nqgym
Version: 1.0.0
Summary: A Python project generator.
Home-page: https://github.com/navy-xie/nqgym
Author: Navy Xie
Author-email: navy.xie@qq.com
License: BSD
Project-URL: Documentation, https://github.com/navy-xie/nqgym/blob/main/README.md
Project-URL: Source Code, https://github.com/navy-xie/nqgym
Keywords: Python,generator,projects,project templates,skeleton,scaffolding,package,cookiecutter
Platform: UNKNOWN
Classifier: Development Status :: 5 - Production/Stable
Classifier: Environment :: Console
Classifier: Intended Audience :: Developers
Classifier: Natural Language :: English
Classifier: License :: OSI Approved :: BSD License
Classifier: Programming Language :: Python :: 3 :: Only
Classifier: Programming Language :: Python :: 3
Classifier: Programming Language :: Python :: 3.7
Classifier: Programming Language :: Python :: 3.8
Classifier: Programming Language :: Python :: 3.9
Classifier: Programming Language :: Python :: Implementation :: CPython
Classifier: Programming Language :: Python
Classifier: Topic :: Software Development
Requires-Python: >=3.6
Provides-Extra: dev
License-File: LICENSE
